{
    "date": "2026-02-15 10:00",
    "stability_index": 46,
    "model_accuracy": 96,
    "global_analysis": "Détérioration continue. Tensions géopolitiques maintenues, climat hors de contrôle (USA toujours hors Accord de Paris), finance fragile. Seule la tech reste dynamique.",
    "pillars": {
        "technologie_ia": {
            "score": 83,
            "comment": "Pragmatisation continue. Modèles spécialisés dominent. Fin de l'ère du scaling aveugle."
        },
        "environnement": {
            "score": 34,
            "comment": "Février 2026 = 0.8°C au-dessus de la moyenne. USA maintient le retrait de l'Accord de Paris. Recul historique."
        },
        "energie": {
            "score": 51,
            "comment": "Prix pétrole stable (~58$/b). Demande électrique IA en hausse. Tensions sur les grilles électriques."
        },
        "geopolitique": {
            "score": 27,
            "comment": "Stagnation Ukraine. Tensions accrues en Mer de Chine (incidents navals). Inde-Pakistan toujours volatiles."
        },
        "demographie_social": {
            "score": 39,
            "comment": "Manifestations massives en Europe (agriculteurs). Polarisation politique accrue. Migrations climatiques en hausse."
        },
        "finance": {
            "score": 43,
            "comment": "Volatilité boursière (+3% puis -2%). Dette mondiale → 98% PIB. Valorisations tech surévaluées."
        },
        "sante_bio": {
            "score": 62,
            "comment": "Situation stable post-pandémique. Surveillance H5N1 renforcée (cas humains sporadiques)."
        },
        "espace": {
            "score": 37,
            "comment": "Militarisation orbitale continue (satellites militaires +12% vs 2025). Starship vols commerciaux stagnants."
        },
        "information": {
            "score": 36,
            "comment": "Guerre hybride Russie-OTAN intensifiée. Deepfakes électoraux massifs. Censure numérique en expansion."
        }
    },
    "alerts": [
        "📅 2030 : la Corruption de la Noosphère catalyse la Friction Géopolitique. Probabilité de rupture : 56%.",
        "⚠️ Ω_BIOSPHERE : Seuil critique dépassé (USA hors Accord de Paris)",
        "⚔️ Σ_CONFLICT : Tensions maximales maintenues",
        "🧠 Δ_NOOSPHERE : Dégradation informationnelle accélérée",
        "💰 Ω_DEBT : Trajectoire insoutenable (98% PIB mondial)"
    ],
    "archives": [
        {
            "year": "1914",
            "score": 30,
            "desc": "Rupture de l'équilibre des alliances"
        },
        {
            "year": "1918",
            "score": 42,
            "desc": "Effondrement démographique viral"
        },
        {
            "year": "1929",
            "score": 45,
            "desc": "Dislocation des vecteurs de crédit"
        },
        {
            "year": "1939",
            "score": 20,
            "desc": "Friction cinétique globale"
        },
        {
            "year": "1945",
            "score": 10,
            "desc": "Entropie géopolitique maximale"
        },
        {
            "year": "1962",
            "score": 62,
            "desc": "Tension nucléaire critique"
        },
        {
            "year": "1973",
            "score": 65,
            "desc": "Choc des ressources fossiles"
        },
        {
            "year": "2001",
            "score": 58,
            "desc": "Asymétrie sécuritaire globale"
        },
        {
            "year": "2008",
            "score": 50,
            "desc": "Toxicité des actifs financiers"
        },
        {
            "year": "2020",
            "score": 45,
            "desc": "Pandémie systémique de classe 4"
        },
        {
            "year": "2022",
            "score": 45,
            "desc": "Retour de la guerre haute intensité"
        }
    ]
}
