{
    "scenarios": {
        "optimiste": [
            {
                "year": "2027",
                "stability_index": 47
            },
            {
                "year": "2028",
                "stability_index": 50
            },
            {
                "year": "2029",
                "stability_index": 42
            },
            {
                "year": "2030",
                "stability_index": 51
            },
            {
                "year": "2031",
                "stability_index": 61
            },
            {
                "year": "2032",
                "stability_index": 65
            },
            {
                "year": "2033",
                "stability_index": 68
            },
            {
                "year": "2034",
                "stability_index": 72
            },
            {
                "year": "2035",
                "stability_index": 75
            },
            {
                "year": "2036",
                "stability_index": 79
            }
        ],
        "tendantielle": [
            {
                "year": "2027",
                "stability_index": 43
            },
            {
                "year": "2028",
                "stability_index": 42
            },
            {
                "year": "2029",
                "stability_index": 30
            },
            {
                "year": "2030",
                "stability_index": 36
            },
            {
                "year": "2031",
                "stability_index": 42
            },
            {
                "year": "2032",
                "stability_index": 41
            },
            {
                "year": "2033",
                "stability_index": 41
            },
            {
                "year": "2034",
                "stability_index": 41
            },
            {
                "year": "2035",
                "stability_index": 40
            },
            {
                "year": "2036",
                "stability_index": 40
            }
        ],
        "pessimiste": [
            {
                "year": "2027",
                "stability_index": 38
            },
            {
                "year": "2028",
                "stability_index": 34
            },
            {
                "year": "2029",
                "stability_index": 18
            },
            {
                "year": "2030",
                "stability_index": 19
            },
            {
                "year": "2031",
                "stability_index": 21
            },
            {
                "year": "2032",
                "stability_index": 16
            },
            {
                "year": "2033",
                "stability_index": 12
            },
            {
                "year": "2034",
                "stability_index": 7
            },
            {
                "year": "2035",
                "stability_index": 3
            },
            {
                "year": "2036",
                "stability_index": 3
            }
        ]
    }
}